{
    "badgePosition": "Placering af mærke",
    "badgePositionDescription": "Placer emblemet i spillets sidehoved",
    "badgeSize": "Mærkets størrelse",
    "badgeSizeDescription": "Vælg en anden størrelse til emblemet",
    "caching": "Cachelagring",
    "clearCache": "Ryd ProtonDB Cache",
    "clearCacheLabel": "Ryd cachen for at tvinge opdatering alle ProtonDB mærker",
    "expandOnHover": "Hold over etiket for at udvide",
    "expandOnHoverDescription": "Minimalistisk. Vis kun emblem tekst ved fokus",
    "positionTopLeft": "Øverst til venstre",
    "positionTopRight": "Øverst til højre",
    "positionBottomLeft": "Bottom Left",
    "positionBottomMiddle": "Bottom Middle",
    "positionBottomRight": "Bottom Right",
    "positionTopMiddle": "Øverst i midten",
    "settings": "Indstillinger",
    "sizeMinimalist": "Minimalistisk",
    "sizeRegular": "Almindelig",
    "sizeSmall": "Lille",
    "tierborked": "VIRKER IKKE",
    "tierbronze": "BRONZE",
    "tiergold": "GULD",
    "tierMinborked": "ITU",
    "tierMinbronze": "BRON",
    "tierMingold": "GULD",
    "tierMinpending": "AFVENT",
    "tierMinplatinum": "PLAT",
    "tierMinsilver": "SØLV",
    "tierpending": "AFVENTER",
    "tierplatinum": "PLATIN",
    "tiersilver": "SØLV",
    "expandOnHoverOff": "Fra",
    "submit": "INDSEND",
    "login": "Log ind",
    "loading": "...",
    "noReport": "INGEN RAPPORT",
    "disableSubmit": "Deaktiver indsendelse",
    "disableSubmitDesc": "Skjul indsendelsesknappen, der tillader bidrag af rapporter til ProtonDB",
    "enableStoreBadge": "Aktiver mærke på butikssider",
    "enableStoreBadgeDesc": "Vis ProtonDB mærke under Steam Deck kompatibilitet på butikssider",
    "originalPluginDetected": "Originalt plugin registreret",
    "originalPluginWarning": "Det originale 'ProtonDB Badges' plugin er stadig installeret. Deaktiver det i Decky indstillingerne for at undgå konflikter med denne udvidede version.",
    "originalPluginVersion": "Version"
}